README.md
setup.py
src/awsglue/__init__.pyi
src/awsglue/context.pyi
src/awsglue/data_sink.pyi
src/awsglue/data_source.pyi
src/awsglue/dataframereader.pyi
src/awsglue/devutils.pyi
src/awsglue/dynamicframe.pyi
src/awsglue/functions.pyi
src/awsglue/glue_shell.pyi
src/awsglue/gluetypes.pyi
src/awsglue/job.pyi
src/awsglue/streaming_data_source.pyi
src/awsglue/utils.pyi
src/awsglue/dataframe_transforms/__init__.pyi
src/awsglue/dataframe_transforms/apply_mapping.pyi
src/awsglue/transforms/__init__.pyi
src/awsglue/transforms/apply_mapping.pyi
src/awsglue/transforms/coalesce.pyi
src/awsglue/transforms/collection_transforms.pyi
src/awsglue/transforms/drop_nulls.pyi
src/awsglue/transforms/dynamicframe_filter.pyi
src/awsglue/transforms/dynamicframe_map.pyi
src/awsglue/transforms/errors_as_dynamicframe.pyi
src/awsglue/transforms/field_transforms.pyi
src/awsglue/transforms/relationalize.pyi
src/awsglue/transforms/repartition.pyi
src/awsglue/transforms/resolve_choice.pyi
src/awsglue/transforms/transform.pyi
src/awsglue/transforms/unbox.pyi
src/awsglue/transforms/union.pyi
src/awsglue/transforms/unnest_frame.pyi
src/awsglue_stubs.egg-info/PKG-INFO
src/awsglue_stubs.egg-info/SOURCES.txt
src/awsglue_stubs.egg-info/dependency_links.txt
src/awsglue_stubs.egg-info/requires.txt
src/awsglue_stubs.egg-info/top_level.txt